setup.py
src/senzafine_analytica/__init__.py
src/senzafine_analytica/models.py
src/senzafine_analytica/resources.py
src/senzafine_analytica.egg-info/PKG-INFO
src/senzafine_analytica.egg-info/SOURCES.txt
src/senzafine_analytica.egg-info/dependency_links.txt
src/senzafine_analytica.egg-info/requires.txt
src/senzafine_analytica.egg-info/top_level.txt