Metadata-Version: 1.0
Name: senzafine-analytica
Version: 0.1
Summary: Senzafine Analytica Service API
Home-page: UNKNOWN
Author: Senzafine.com.br
Author-email: thiago@senzafine.com.br
License: UNKNOWN
Platform: UNKNOWN
Classifier: Topic :: Scientific/Engineering :: Artificial Intelligence
Classifier: Topic :: Software Development :: Libraries :: Python Modules
Classifier: License :: Freely Distributable
